{
"title":"gamma_valerlolactone",
"structure": [
    "O",  1.280090,   -0.110219,  0.176701,
    "C",  2.492496,   -0.048697,  0.049467,
    "C",  3.321819,    1.190045,  0.131323,
    "C",  4.445834,    0.825653, -0.804104,
    "C",  4.595333,   -0.668962, -0.597343,
    "C",  5.708061,   -0.998337,  0.387641,
    "O",  3.316504,   -1.124551, -0.137839,
    "H",  2.778504,    2.076626, -0.201053,
    "H",  3.659613,    1.313773,  1.165041,
    "H",  5.361582,    1.394137, -0.621274,
    "H",  4.134877,    1.015175, -1.838892,
    "H",  4.803515,   -1.174071, -1.546167,
    "H",  5.791907,   -2.078842,  0.539638,
    "H",  6.667833,   -0.631778,  0.005306,
    "H",  5.532499,   -0.545580,  1.368709
],
"charge" : 0,
"mult" : 1,

"conformer_search" : 0,
"reaction_search" : 1,
"rotor_scan" : 0,
"high_level" : 0,
"barrier_threshold" : 200.0,
"skip_families": ["hom_sci"],

"queuing": "<slurm or pbs>",
"queue_name":"<name of your queue>",
"queue_job_limit": 100,
"ppn": <num_processors_per_job>,

"qc" : "gauss",
"method" : "b3lyp",
"basis" : "6-31+g*"
}
